alphad3m_containers/__init__.py
alphad3m_containers/api.py
alphad3m_containers-0.24.0.dist-info/LICENSE.txt
alphad3m_containers-0.24.0.dist-info/METADATA
alphad3m_containers-0.24.0.dist-info/NOTICE.txt
alphad3m_containers-0.24.0.dist-info/WHEEL
alphad3m_containers-0.24.0.dist-info/top_level.txt
alphad3m_containers-0.24.0.dist-info/RECORD
