Metadata-Version: 2.1
Name: alphad3m-containers
Version: 0.24.0
Summary: AlphaD3M: NYU's AutoML System
Home-page: https://gitlab.com/ViDA-NYU/d3m/alphad3m
Author: Remi Rampin, Roque Lopez
Author-email: remi.rampin@nyu.edu, rlopez@nyu.edu
Maintainer: Remi Rampin, Roque Lopez
Maintainer-email: remi.rampin@nyu.edu, rlopez@nyu.edu
License: Apache-2.0
Keywords: datadrivendiscovery,automl,d3m,ta2,nyu
Platform: UNKNOWN
Classifier: Development Status :: 5 - Production/Stable
Classifier: Intended Audience :: Science/Research
Classifier: License :: OSI Approved :: Apache Software License
Classifier: Topic :: Scientific/Engineering
License-File: LICENSE.txt
License-File: NOTICE.txt
Requires-Dist: d3m-interface
